LICENSE
MANIFEST.in
README.rst
setup.py
sound_server/__init__.py
sound_server/auto_sounds.py
sound_server/derivative_estimator.py
sound_server/smooth.py
sound_server/sound_channel_group.py
sound_server/sound_global_state.py
sound_server/sound_object.py
sound_server/sound_server.py
sound_server/spline.py
sound_server.egg-info/PKG-INFO
sound_server.egg-info/SOURCES.txt
sound_server.egg-info/dependency_links.txt
sound_server.egg-info/not-zip-safe
sound_server.egg-info/requires.txt
sound_server.egg-info/top_level.txt