Metadata-Version: 1.1
Name: sound-server
Version: 0.1.1
Summary: A Python-based sound server, allowing control of the FModEx API via OSC messages.
Home-page: http://github.com/johnhw/sound_server
Author: John Williamson
Author-email: johnhw@gmail.com
License: MIT
Keywords: sound OSC FModEx server
Platform: UNKNOWN
Classifier: Development Status :: 3 - Alpha
Classifier: License :: OSI Approved :: MIT License
Classifier: Programming Language :: Python :: 2.7
Classifier: Topic :: Multimedia :: Sound/Audio
Classifier: Topic :: Multimedia :: Sound/Audio :: Players
